djctools/__init__.py
djctools/module_extensions.py
djctools/training.py
djctools/wandb_tools.py
djctools-0.1.1.dist-info/METADATA
djctools-0.1.1.dist-info/WHEEL
djctools-0.1.1.dist-info/top_level.txt
djctools-0.1.1.dist-info/RECORD
