Metadata-Version: 2.2
Name: djctools
Version: 0.1.1
Summary: A package for logging, loss management, and multi-GPU training. Follows the core ideas of DeepJetCore but in torch.
Author-email: Jan Kieseler <jan.kieseler@cern.ch>
License: MIT
Classifier: Programming Language :: Python :: 3
Classifier: License :: OSI Approved :: MIT License
Classifier: Operating System :: OS Independent
Requires-Python: >=3.7
Requires-Dist: numpy
Requires-Dist: wandb
Requires-Dist: torch
